cg635_clock_generator/__init__.py
cg635_clock_generator/_cg635_clock_generator.py
cg635_clock_generator/_constants.py
cg635_clock_generator/_exceptions.py
cg635_clock_generator/py.typed
cg635_clock_generator-1.1.0.dist-info/METADATA
cg635_clock_generator-1.1.0.dist-info/WHEEL
cg635_clock_generator-1.1.0.dist-info/licenses/LICENSE.txt
cg635_clock_generator-1.1.0.dist-info/RECORD
