Metadata-Version: 2.4
Name: cg635-clock-generator
Version: 1.1.0
Summary: Interface with a Stanford Research Systems CG635 Synthesized Clock Generator
Project-URL: Source, https://gitlab.desy.de/leandro.lanzieri/cg635-clock-generator
Project-URL: Documentation, https://cg635-clock-generator-leandro-lanzieri-c9d5fa14e6af42e02aa27f45.pages.desy.de
Author-email: Leandro Lanzieri <leandro.lanzieri@desy.de>
License-Expression: LGPL-3.0-or-later
License-File: LICENSE.txt
Classifier: Development Status :: 5 - Production/Stable
Classifier: Programming Language :: Python
Requires-Python: >=3.10
Requires-Dist: pyserial
Requires-Dist: pyvisa
Requires-Dist: pyvisa-py
